fabricatio_improve/__init__.py
fabricatio_improve/config.py
fabricatio_improve/py.typed
fabricatio_improve/actions/__init__.py
fabricatio_improve/capabilities/__init__.py
fabricatio_improve/capabilities/correct.py
fabricatio_improve/capabilities/review.py
fabricatio_improve/models/__init__.py
fabricatio_improve/models/improve.py
fabricatio_improve/models/kwargs_types.py
fabricatio_improve/models/problem.py
fabricatio_improve/workflows/__init__.py
tests/test_correct.py
tests/test_review.py
fabricatio_improve-0.1.10.dist-info/METADATA
fabricatio_improve-0.1.10.dist-info/WHEEL
fabricatio_improve-0.1.10.dist-info/licenses/LICENSE
fabricatio_improve-0.1.10.dist-info/RECORD
