Metadata-Version: 2.4
Name: fabricatio-improve
Version: 0.1.10
Summary: A Python library for content review, correction, and improvement in LLM applications.
Project-URL: Homepage, https://github.com/Whth/fabricatio
Project-URL: Repository, https://github.com/Whth/fabricatio
Project-URL: Issues, https://github.com/Whth/fabricatio/issues
Author-email: Whth <zettainspector@foxmail.com>
License: MIT License
License-File: LICENSE
Requires-Python: <3.15,>=3.12
Requires-Dist: fabricatio-capabilities
Requires-Dist: fabricatio-core
Requires-Dist: fabricatio-question
